pymeth/__init__.py
pymeth/constants.py
pymeth/algorithms/__init__.py
pymeth/algorithms/binarysearch.py
pymeth/algorithms/quicksort.py
pymeth-1.0.1.dist-info/LICENSE
pymeth-1.0.1.dist-info/METADATA
pymeth-1.0.1.dist-info/WHEEL
pymeth-1.0.1.dist-info/top_level.txt
pymeth-1.0.1.dist-info/RECORD
