Metadata-Version: 2.1
Name: pymeth
Version: 1.0.1
Summary: A python package for using basic math algorithm
Home-page: https://github.com/saurabhmehta1601/pymeth.git
Download-URL: https://github.com/saurabhmehta1601/pymeth.git
Author: Saurabh Mehta
Author-email: saurabhmehta1601@gmail.com
Maintainer: Saurabh Mehta
Maintainer-email: saurabhmehta1601@gmail.com
License: MIT
Project-URL: Bug Tracker, https://github.com/saurabhmehta1601/pymeth/issues
Keywords: Math,Algorithm,Binary Search
Requires-Python: >=3.6
License-File: LICENSE
